graph_algo_vis/__init__.py
graph_algo_vis/bfs_traversal.py
graph_algo_vis/dfs_traversal.py
graph_algo_vis/kruskalsMST.py
graph_algo_vis/primsMST.py
graph_algo_vis/topological_sort.py
graph_algo_vis-0.3.dist-info/METADATA
graph_algo_vis-0.3.dist-info/WHEEL
graph_algo_vis-0.3.dist-info/top_level.txt
graph_algo_vis-0.3.dist-info/RECORD
