Metadata-Version: 2.1
Name: graph-algo-vis
Version: 0.3
Summary: Visualize Graph Algorithms
Home-page: http://akrashsharma.netlify.app/
Author: Akrash Sharma
Author-email: akarshsharma654@gmail.com
License: UNKNOWN
Project-URL: Graph Algorithms Visualization, https://github.com/Akarsh654/Graph-Algorithms-Package
Keywords: Graph,Algorithms,BFS,DFS,Topological Sort,Prim's MST,Kruskal's MST
Platform: UNKNOWN
Classifier: Programming Language :: Python :: 3.6
Classifier: Programming Language :: Python :: 3.7
Classifier: License :: OSI Approved :: MIT License
Classifier: Operating System :: OS Independent
Requires-Python: >=3.6
Requires-Dist: networkx
Requires-Dist: matplotlib
Provides-Extra: dev
Requires-Dist: networkx ; extra == 'dev'
Requires-Dist: matplotlib ; extra == 'dev'
